lt8900_spi/__init__.py
lt8900_spi-2.6.dist-info/LICENSE
lt8900_spi-2.6.dist-info/METADATA
lt8900_spi-2.6.dist-info/WHEEL
lt8900_spi-2.6.dist-info/top_level.txt
lt8900_spi-2.6.dist-info/RECORD
