Metadata-Version: 2.1
Name: lt8900-spi
Version: 2.6
Summary: Python interface to an LT8900 connected via SPI
Home-page: https://chiselapp.com/user/rkeene/repository/lt8900_spi/
Author: Roy Keene
Author-email: pypi@rkeene.org
License: MIT License
Platform: UNKNOWN
Classifier: Programming Language :: Python :: 3
Classifier: License :: OSI Approved :: MIT License
Classifier: Operating System :: OS Independent
Requires-Python: >=3.6
Requires-Dist: spidev (>=3.0.0)
